[
  {
    "name": "Вітрильний спорт",
    "image": "img/card-act.png",
    "price": 500
  },
  {
    "name": "Скелелазіння",
    "image": "img/card-act1.png",
    "price": 100
  },
  {
    "name": "Катання на лижах",
    "image": "img/card-act2.png",
    "price": 150
  },
  {
    "name": "Піші прогулянки",
    "image": "img/card-act3.png",
    "price": 50
  },
  {
    "name": "Зоопарки та природні парки",
    "image": "img/card-act4.jpg",
    "price": 60
  },
  {
    "name": "Плавання з маскою і трубкою",
    "image": "img/card-act5.png",
    "price": 400
  }
]
